{"$schema":"https://vega.github.io/schema/vega-lite/v5.json","title":"Country Development Indicators","mark":{"type":"circle","opacity":0.7},"data":{"values":[{"country":"USA","gdp":65000,"lifeExpectancy":78,"population":330},{"country":"China","gdp":12000,"lifeExpectancy":77,"population":1400},{"country":"India","gdp":2500,"lifeExpectancy":70,"population":1380},{"country":"Germany","gdp":48000,"lifeExpectancy":81,"population":83},{"country":"Brazil","gdp":9000,"lifeExpectancy":76,"population":213},{"country":"Japan","gdp":40000,"lifeExpectancy":84,"population":126},{"country":"Nigeria","gdp":2200,"lifeExpectancy":55,"population":206}]},"encoding":{"x":{"field":"gdp","type":"quantitative","axis":{"title":"GDP per Capita ($)"}},"y":{"field":"lifeExpectancy","type":"quantitative","axis":{"title":"Life Expectancy (years)"},"scale":{"zero":false}},"size":{"field":"population","type":"quantitative","legend":{"title":"Population (M)"}},"color":{"field":"country","type":"nominal","legend":{"title":"Country"}}}}