{
  "data": [
    {
      "type": "heatmap",
      "z": [
        [
          10,
          20,
          30,
          40,
          50,
          60,
          70,
          80,
          90,
          100,
          110,
          120
        ],
        [
          15,
          25,
          35,
          45,
          55,
          65,
          75,
          85,
          95,
          105,
          115,
          125
        ],
        [
          5,
          10,
          15,
          20,
          25,
          30,
          35,
          40,
          45,
          50,
          55,
          60
        ]
      ],
      "x": [
        "Jan",
        "Feb",
        "Mar",
        "Apr",
        "May",
        "Jun",
        "Jul",
        "Aug",
        "Sep",
        "Oct",
        "Nov",
        "Dec"
      ],
      "y": [
        "Category A",
        "Category B",
        "Category C"
      ],
      "colorscale": [
        [
          0.0,
          "rgb(158,1,66)"
        ],
        [
          0.1,
          "rgb(213,62,79)"
        ],
        [
          0.2,
          "rgb(244,109,67)"
        ],
        [
          0.3,
          "rgb(253,174,97)"
        ],
        [
          0.4,
          "rgb(254,224,139)"
        ],
        [
          0.5,
          "rgb(255,255,191)"
        ],
        [
          0.6,
          "rgb(230,245,152)"
        ],
        [
          0.7,
          "rgb(171,221,164)"
        ],
        [
          0.8,
          "rgb(102,194,165)"
        ],
        [
          0.9,
          "rgb(50,136,189)"
        ],
        [
          1.0,
          "rgb(94,79,162)"
        ]
      ]
    }
  ],
  "layout": {
    "title": "Sales Intensity Across Months and Categories",
    "xaxis": {
      "title": "Month"
    },
    "yaxis": {
      "title": "Category"
    }
  },
  "id": 8
}